daemon/__init__.py
daemon/cmdline.py
daemon/version.py
daemon/mac/__init__.py
daemon/mac/launchy.py
daemon/termux/__init__.py
daemon/termux/svctl.py
daemon/termux/svmanager.py
daemon/utils/__init__.py
launchy-0.0.7.dist-info/METADATA
launchy-0.0.7.dist-info/WHEEL
launchy-0.0.7.dist-info/entry_points.txt
launchy-0.0.7.dist-info/top_level.txt
launchy-0.0.7.dist-info/RECORD
