Metadata-Version: 2.1
Name: launchy
Version: 0.0.7
Summary: system launchy
Author-email: Seven <1162584980@qq.com>
Maintainer-email: Seven <1162584980@qq.com>
License: MIT License
Classifier: Topic :: Utilities
Classifier: Programming Language :: Python :: 3
Classifier: License :: OSI Approved :: MIT License
Classifier: Operating System :: OS Independent
Requires-Python: >=3.8
Requires-Dist: prettytable
Requires-Dist: psutil
